MANIFEST.in
README.rst
setup.py
yametrikapy/__init__.py
yametrikapy/client.py
yametrikapy/core.py
yametrikapy.egg-info/PKG-INFO
yametrikapy.egg-info/SOURCES.txt
yametrikapy.egg-info/dependency_links.txt
yametrikapy.egg-info/not-zip-safe
yametrikapy.egg-info/top_level.txt
yametrikapy/tests/__init__.py
yametrikapy/tests/test_yametrikapy.py