Metadata-Version: 1.1
Name: yametrikapy
Version: 2.0
Summary: UNKNOWN
Home-page: https://github.com/pikhovkin/yametrikapy/
Author: Sergey Pikhovkin
Author-email: s@pikhovkin.ru
License: MIT
Keywords: yandex metrika api
Platform: UNKNOWN
Classifier: Intended Audience :: Developers
Classifier: License :: OSI Approved :: MIT License
Classifier: Environment :: Web Environment
Classifier: Natural Language :: Russian
Classifier: Natural Language :: English
Classifier: Operating System :: OS Independent
Classifier: Programming Language :: Python :: 3
Classifier: Topic :: Software Development :: Libraries :: Python Modules
